epmodel/__init__.py
epmodel/builder.py
epmodel/epmodel.py
epmodel-0.10.0.dist-info/licenses/LICENSE
epmodel-0.10.0.dist-info/METADATA
epmodel-0.10.0.dist-info/WHEEL
epmodel-0.10.0.dist-info/top_level.txt
epmodel-0.10.0.dist-info/RECORD
