Metadata-Version: 2.4
Name: epmodel
Version: 0.10.0
Summary: Data models for EnergyPlus automatically generated from EnergyPlus JSON schema using datamodel-code-generator.
Author-email: Taoning Wang <taoningwang@lbl.gov>
License: Copyright (c) 2023, The Regents of the University of California,
Requires-Python: >=3.9
License-File: LICENSE
Requires-Dist: pydantic>=2.3.0
Dynamic: license-file
